LICENSE
MANIFEST.in
README.md
requirements.txt
setup.py
marshmallow_dumped_order/__init__.py
marshmallow_dumped_order/dumped_order.py
marshmallow_dumped_order.egg-info/PKG-INFO
marshmallow_dumped_order.egg-info/SOURCES.txt
marshmallow_dumped_order.egg-info/dependency_links.txt
marshmallow_dumped_order.egg-info/not-zip-safe
marshmallow_dumped_order.egg-info/requires.txt
marshmallow_dumped_order.egg-info/top_level.txt