Metadata-Version: 2.1
Name: marshmallow-dumped-order
Version: 1.0.0
Summary: Decorator for `marshmallow.Schema` to sort fields in needed order while dumping
Home-page: https://github.com/maximdanilchenko/marshmallow-dumped-order
Author: Danilchenko Maksim
Author-email: dmax.dev@gmail.com
License: MIT
Keywords: marshmallow schema dump fields order
Platform: UNKNOWN
Classifier: Development Status :: 4 - Beta
Classifier: Intended Audience :: Developers
Classifier: License :: OSI Approved :: MIT License
Classifier: Natural Language :: English
Classifier: Programming Language :: Python
Classifier: Programming Language :: Python :: 3.6
Classifier: Programming Language :: Python :: 3.7
Classifier: Programming Language :: Python :: 3 :: Only
